Workbook
Name StartingBalance: Récapitulatif!$L$8

Sheet Récapitulatif
B2: PREMIERS PAS | I2: REMARQUE
B3: Définissez votre solde de départ dans la cellule L8, personnalisez les catégories, puis saisissez le montant des recettes et dépenses prévues dans les tableaux "Revenus" et "Dépenses" ci-dessous. | I3: Ne modifiez que les cellules ayant une couleur de remplissage.
I4: Essayez de ne pas modifier les cellules contenant une formule.
B5: Lorsque vous saisissez des données dans la feuille "Transactions", cette feuille est mise à jour automatiquement de manière à présenter un récapitulatif de vos dépenses du mois.
B8: Budget Eté | J8: Solde de départ : | L8: 1000
D12: =IFERROR(__xludf.DUMMYFUNCTION("SPARKLINE(D17,{""charttype"",""column"";""ymin"", 0; ""ymax"",MAX(D17:E17);""firstcolor"",""#334960""})"),"") | E12: =IFERROR(__xludf.DUMMYFUNCTION("SPARKLINE(E17,{""charttype"",""column"";""ymin"", 0; ""ymax"",max(D17:E17);""firstcolor"",""#f46524""})"),"")
I13: =IFERROR(E17/D17-1, "") -> 0
I14: =IF(I13 < 0, "de baisse des économies totales", "d'augmentation des économies totales") -> d'augmentation des économies totales
I15: =IFERROR(E17-D17, 0) -> 0
D16: SOLDE DE DÉPART | E16: SOLDE FINAL | I16: =IF(J15<0, "dépensés ce mois-ci", "économisés ce mois-ci") -> économisés ce mois-ci
D17: =IF(ISBLANK(L8),0,L8) -> 1000 | E17: =D17+(I22-C22) -> 1000
B20: Dépenses | H20: Revenus
B21: Prévues | C21: =D26 -> 760.4 | D21: =IFERROR(__xludf.DUMMYFUNCTION("SPARKLINE(C21,{""charttype"",""bar"";""max"",max(C21:C22);""color1"",""#AEB7C0""})"),"") | H21: Prévus | I21: =J26 -> 629.4 | J21: =IFERROR(__xludf.DUMMYFUNCTION("SPARKLINE(I21,{""charttype"",""bar"";""max"",max(I21:I22);""color1"",""#AEB7C0""})"),"")
B22: Réelles | C22: =E26 -> 0 | D22: =IFERROR(__xludf.DUMMYFUNCTION("SPARKLINE(C22,{""charttype"",""bar"";""max"",max(C21:C22);""color1"",""#334960""})"),"") | H22: Réels | I22: =K26 -> 0 | J22: =IFERROR(__xludf.DUMMYFUNCTION("SPARKLINE(I22,{""charttype"",""bar"";""max"",max(I21:I22);""color1"",""#334960""})"),"")
B24: Dépenses | H24: Revenus
D25: Prévues | E25: Réelles | F25: Diff. | J25: Prévus | K25: Réels | L25: Diff.
B26: Totaux | D26: =SUM(D27:D44) -> 760.4 | E26: =SUM(E27:E44) -> 0 | F26: =SUM(F27:F44) -> 760.4 | H26: Totaux | J26: =SUM(J27:J44) -> 629.4 | K26: =SUM(K27:K44) -> 0 | L26: =SUM(L27:L44) -> -629.4
E27: =IF(ISBLANK($B27), "", SUMIF(Transactions!$E:$E,$B27,Transactions!$C:$C)) | F27: =IF(ISBLANK($B27), "", D27-E27) | K27: =IF(ISBLANK($H27), "", SUMIF(Transactions!$J:$J,$H27,Transactions!$H:$H)) | L27: =IF(ISBLANK($H27), "", K27-J27)
B28: Alimentation | D28: =700/4 -> 175 | E28: =IF(ISBLANK($B28), "", SUMIF(Transactions!$E:$E,$B28,Transactions!$C:$C)) -> 0 | F28: =IF(ISBLANK($B28), "", D28-E28) -> 175 | H28: Épargne | K28: =IF(ISBLANK($H28), "", SUMIF(Transactions!$J:$J,$H28,Transactions!$H:$H)) -> 0 | L28: =IF(ISBLANK($H28), "", K28-J28) -> 0
B29: Cadeaux | D29: =130/4 -> 32.5 | E29: =IF(ISBLANK($B29), "", SUMIF(Transactions!$E:$E,$B29,Transactions!$C:$C)) -> 0 | F29: =IF(ISBLANK($B29), "", D29-E29) -> 32.5 | H29: Salaire | K29: =IF(ISBLANK($H29), "", SUMIF(Transactions!$J:$J,$H29,Transactions!$H:$H)) -> 0 | L29: =IF(ISBLANK($H29), "", K29-J29) -> 0
B30: Santé/médecine | D30: =5 -> 5 | E30: =IF(ISBLANK($B30), "", SUMIF(Transactions!$E:$E,$B30,Transactions!$C:$C)) -> 0 | F30: =IF(ISBLANK($B30), "", D30-E30) -> 5 | H30: Bonus | K30: =IF(ISBLANK($H30), "", SUMIF(Transactions!$J:$J,$H30,Transactions!$H:$H)) -> 0 | L30: =IF(ISBLANK($H30), "", K30-J30) -> 0
B31: Habitation | D31: 0 | E31: =IF(ISBLANK($B31), "", SUMIF(Transactions!$E:$E,$B31,Transactions!$C:$C)) -> 0 | F31: =IF(ISBLANK($B31), "", D31-E31) -> 0 | H31: Intérêts | J31: 329.4 | K31: =IF(ISBLANK($H31), "", SUMIF(Transactions!$J:$J,$H31,Transactions!$H:$H)) -> 0 | L31: =IF(ISBLANK($H31), "", K31-J31) -> -329.4
B32: Transports | D32: 60 | E32: =IF(ISBLANK($B32), "", SUMIF(Transactions!$E:$E,$B32,Transactions!$C:$C)) -> 0 | F32: =IF(ISBLANK($B32), "", D32-E32) -> 60 | H32: Autres | K32: =IF(ISBLANK($H32), "", SUMIF(Transactions!$J:$J,$H32,Transactions!$H:$H)) -> 0 | L32: =IF(ISBLANK($H32), "", K32-J32) -> 0
B33: Dépenses personnelles | D33: =150/4 -> 37.5 | E33: =IF(ISBLANK($B33), "", SUMIF(Transactions!$E:$E,$B33,Transactions!$C:$C)) -> 0 | F33: =IF(ISBLANK($B33), "", D33-E33) -> 37.5 | H33: Remboursements | K33: =IF(ISBLANK($H33), "", SUMIF(Transactions!$J:$J,$H33,Transactions!$H:$H)) -> 0 | L33: =IF(ISBLANK($H33), "", K33-J33) -> 0
B34: Animaux de compagnie | E34: =IF(ISBLANK($B34), "", SUMIF(Transactions!$E:$E,$B34,Transactions!$C:$C)) -> 0 | F34: =IF(ISBLANK($B34), "", D34-E34) -> 0 | H34: Maman | J34: 300 | K34: =IF(ISBLANK($H34), "", SUMIF(Transactions!$J:$J,$H34,Transactions!$H:$H)) -> 0 | L34: =IF(ISBLANK($H34), "", K34-J34) -> -300
B35: Électricité, eau, gaz... | E35: =IF(ISBLANK($B35), "", SUMIF(Transactions!$E:$E,$B35,Transactions!$C:$C)) -> 0 | F35: =IF(ISBLANK($B35), "", D35-E35) -> 0 | K35: =IF(ISBLANK($H35), "", SUMIF(Transactions!$J:$J,$H35,Transactions!$H:$H)) | L35: =IF(ISBLANK($H35), "", K35-J35)
B36: Voyage | E36: =IF(ISBLANK($B36), "", SUMIF(Transactions!$E:$E,$B36,Transactions!$C:$C)) -> 0 | F36: =IF(ISBLANK($B36), "", D36-E36) -> 0 | K36: =IF(ISBLANK($H36), "", SUMIF(Transactions!$J:$J,$H36,Transactions!$H:$H)) | L36: =IF(ISBLANK($H36), "", K36-J36)
B37: Avec Adèle | D37: =40 -> 40 | E37: =IF(ISBLANK($B37), "", SUMIF(Transactions!$E:$E,$B37,Transactions!$C:$C)) -> 0 | F37: =IF(ISBLANK($B37), "", D37-E37) -> 40 | K37: =IF(ISBLANK($H37), "", SUMIF(Transactions!$J:$J,$H37,Transactions!$H:$H)) | L37: =IF(ISBLANK($H37), "", K37-J37)
B38: Autres | D38: =30/4 -> 7.5 | E38: =IF(ISBLANK($B38), "", SUMIF(Transactions!$E:$E,$B38,Transactions!$C:$C)) -> 0 | F38: =IF(ISBLANK($B38), "", D38-E38) -> 7.5 | K38: =IF(ISBLANK($H38), "", SUMIF(Transactions!$J:$J,$H38,Transactions!$H:$H)) | L38: =IF(ISBLANK($H38), "", K38-J38)
B39: Remboursements | D39: 329.4 | E39: =IF(ISBLANK($B39), "", SUMIF(Transactions!$E:$E,$B39,Transactions!$C:$C)) -> 0 | F39: =IF(ISBLANK($B39), "", D39-E39) -> 329.4 | K39: =IF(ISBLANK($H39), "", SUMIF(Transactions!$J:$J,$H39,Transactions!$H:$H)) | L39: =IF(ISBLANK($H39), "", K39-J39)
B40: Restaurants | D40: =200/4 -> 50 | E40: =IF(ISBLANK($B40), "", SUMIF(Transactions!$E:$E,$B40,Transactions!$C:$C)) -> 0 | F40: =IF(ISBLANK($B40), "", D40-E40) -> 50 | K40: =IF(ISBLANK($H40), "", SUMIF(Transactions!$J:$J,$H40,Transactions!$H:$H)) | L40: =IF(ISBLANK($H40), "", K40-J40)
B41: Bars | D41: =94/4 -> 23.5 | E41: =IF(ISBLANK($B41), "", SUMIF(Transactions!$E:$E,$B41,Transactions!$C:$C)) -> 0 | F41: =IF(ISBLANK($B41), "", D41-E41) -> 23.5 | K41: =IF(ISBLANK($H41), "", SUMIF(Transactions!$J:$J,$H41,Transactions!$H:$H)) | L41: =IF(ISBLANK($H41), "", K41-J41)
E44: =IF(ISBLANK($B44), "", SUMIF(Transactions!$E:$E,$B44,Transactions!$C:$C)) | F44: =IF(ISBLANK($B44), "", D44-E44) | K44: =IF(ISBLANK($H44), "", SUMIF(Transactions!$J:$J,$H44,Transactions!$H:$H)) | L44: =IF(ISBLANK($H44), "", K44-J44)

Sheet Transactions
B1: Pour modifier ou ajouter des catégories, modifiez les tableaux "Dépenses" et "Revenus" de la feuille "Récapitulatif".
B2: Dépenses | G2: Revenus
B4: Date | C4: Montant | D4: Description | E4: Catégorie | G4: Date | H4: Montant | I4: Description | J4: Catégorie
